weaver/__init__.py
weaver/_weaver.cpython-311-x86_64-linux-gnu.so
weaver/_weaver.pyi
weaver/cli/__init__.py
weaver/cli/analyze.py
weaver/cli/categorize.py
weaver/cli/contingency.py
weaver/cli/extract.py
weaver/cli/failures.py
weaver/cli/provider.py
weaver/cli/validate.py
hgvs_weaver-0.1.1.dist-info/METADATA
hgvs_weaver-0.1.1.dist-info/WHEEL
hgvs_weaver-0.1.1.dist-info/entry_points.txt
hgvs_weaver-0.1.1.dist-info/RECORD
hgvs_weaver-0.1.1.dist-info/licenses/LICENSE
