Metadata-Version: 2.4
Name: hgvs-weaver
Version: 0.1.1
Requires-Dist: maturin>=1.11.5
Requires-Dist: pysam ; extra == 'validation'
Requires-Dist: tqdm ; extra == 'validation'
Requires-Dist: parsley ; extra == 'validation'
Requires-Dist: bioutils ; extra == 'validation'
Provides-Extra: validation
License-File: LICENSE
Summary: High-performance HGVS parser for Python (Rust powered)
Requires-Python: >=3.10
